gcoin/__init__.py
gcoin/deterministic.py
gcoin/main.py
gcoin/py2specials.py
gcoin/py3specials.py
gcoin/ripemd.py
gcoin/script.py
gcoin/transaction.py
pallium/__init__.py
pallium/deterministic.py
pallium/main.py
pallium/py2specials.py
pallium/py3specials.py
pallium/ripemd.py
pallium/script.py
pallium/transaction.py
pallium-1.1.48.data/data/LICENSE
pallium-1.1.48.dist-info/DESCRIPTION.rst
pallium-1.1.48.dist-info/METADATA
pallium-1.1.48.dist-info/RECORD
pallium-1.1.48.dist-info/WHEEL
pallium-1.1.48.dist-info/metadata.json
pallium-1.1.48.dist-info/top_level.txt
