Metadata-Version: 2.0
Name: pallium
Version: 1.1.48
Summary: Python Bitcoin Tools
Home-page: UNKNOWN
Author: lbyyy
Author-email: developer@diqi.us
License: UNKNOWN
Platform: UNKNOWN
